{
    "taskDefinitionArn": "arn:aws:ecs:us-east-1:272133924862:task-definition/check-task-definition:1",
    "containerDefinitions": [
        {
            "name": "test",
            "image": "272133924862.dkr.ecr.us-east-1.amazonaws.com/pipeline-service-ecr:latest",
            "cpu": 0,
            "portMappings": [],
            "essential": true,
            "environment": [],
            "environmentFiles": [],
            "mountPoints": [],
            "volumesFrom": [],
            "ulimits": []
        }
    ],
    "family": "check-task-definition",
    "revision": 1,
    "volumes": [],
    "status": "ACTIVE",
    "requiresAttributes": [
        {
            "name": "com.amazonaws.ecs.capability.ecr-auth"
        },
        {
            "name": "com.amazonaws.ecs.capability.docker-remote-api.1.18"
        }
    ],
    "placementConstraints": [],
    "compatibilities": [
        "EXTERNAL",
        "EC2"
    ],
    "cpu": "512",
    "memory": "1024",
    "registeredAt": "2024-02-09T06:00:07.850Z",
    "registeredBy": "arn:aws:sts::272133924862:assumed-role/pipeline-service-ecs-deployment-role/skyu-pipeline-assume-role-session",
    "tags": []
}
